{"deaths": 289, "latest_sit_report": {"no": 209, "url": "https://drive.google.com/file/d/1-zbubLsy4UhmCKUXhBPSB6Bjy4hEKcFZ/view", "created_at": "2020-09-05T13:49:01.344Z", "updated_at": "2020-09-05T13:49:01.344Z", "__v": 0, "date": "2020-09-05", "_id": "5f53974d56814c0bcae1e79f", "type": "MOHP"}, "in_isolation": 17027, "tested_total": 768345, "updated_at": "2020-09-06T00:00:00.000Z", "tested_rdt": 312402, "quarantined": 4703, "source": "https://drive.google.com/file/d/1-zbubLsy4UhmCKUXhBPSB6Bjy4hEKcFZ/view", "tested_negative": 722088, "tested_positive": 46257, "pending_result": 0, "recovered": 28941}